[
  {
    "category": "Plazo Fijo",
    "total_clicks": 13083,
    "provider_count": 35,
    "top_providers": [
      {
        "provider": "Banco Voii",
        "clicks": 2230
      },
      {
        "provider": "Banco CMF",
        "clicks": 1436
      },
      {
        "provider": "Crédito Regional",
        "clicks": 1161
      },
      {
        "provider": "Banco Galicia",
        "clicks": 1051
      },
      {
        "provider": "Banco BICA",
        "clicks": 875
      }
    ]
  },
  {
    "category": "Otro",
    "total_clicks": 12075,
    "provider_count": 25,
    "top_providers": [
      {
        "provider": "Dub.link",
        "clicks": 6302
      },
      {
        "provider": "Arqfinance",
        "clicks": 1665
      },
      {
        "provider": "Nexo",
        "clicks": 1402
      },
      {
        "provider": "DolarApp",
        "clicks": 1306
      },
      {
        "provider": "LB",
        "clicks": 314
      }
    ]
  },
  {
    "category": "Money Market",
    "total_clicks": 8348,
    "provider_count": 24,
    "top_providers": [
      {
        "provider": "IOL",
        "clicks": 2195
      },
      {
        "provider": "Cocos",
        "clicks": 1305
      },
      {
        "provider": "Dub.link",
        "clicks": 1042
      },
      {
        "provider": "Mercado Pago",
        "clicks": 970
      },
      {
        "provider": "Balanz",
        "clicks": 843
      }
    ]
  },
  {
    "category": "Cuenta Remunerada",
    "total_clicks": 6659,
    "provider_count": 7,
    "top_providers": [
      {
        "provider": "Banco Nación",
        "clicks": 2512
      },
      {
        "provider": "Carrefour Banco",
        "clicks": 2306
      },
      {
        "provider": "Ualá",
        "clicks": 911
      },
      {
        "provider": "Reba",
        "clicks": 540
      },
      {
        "provider": "Supervielle",
        "clicks": 275
      }
    ]
  },
  {
    "category": "Billetera",
    "total_clicks": 4954,
    "provider_count": 10,
    "top_providers": [
      {
        "provider": "AstroPay",
        "clicks": 1774
      },
      {
        "provider": "Mercado Pago",
        "clicks": 1420
      },
      {
        "provider": "Lemon",
        "clicks": 466
      },
      {
        "provider": "Prex",
        "clicks": 372
      },
      {
        "provider": "Fiwind",
        "clicks": 300
      }
    ]
  },
  {
    "category": "Renta Fija",
    "total_clicks": 3969,
    "provider_count": 9,
    "top_providers": [
      {
        "provider": "IOL",
        "clicks": 1478
      },
      {
        "provider": "Dub.link",
        "clicks": 1237
      },
      {
        "provider": "Banco Galicia",
        "clicks": 480
      },
      {
        "provider": "Balanz",
        "clicks": 340
      },
      {
        "provider": "Ualá",
        "clicks": 144
      }
    ]
  },
  {
    "category": "Página Amiga",
    "total_clicks": 2821,
    "provider_count": 9,
    "top_providers": [
      {
        "provider": "comparadolar.ar",
        "clicks": 1083
      },
      {
        "provider": "dolarito.ar",
        "clicks": 379
      },
      {
        "provider": "enqueinvierto.ar",
        "clicks": 304
      },
      {
        "provider": "comparapix.ar",
        "clicks": 289
      },
      {
        "provider": "betece.app",
        "clicks": 237
      }
    ]
  },
  {
    "category": "General",
    "total_clicks": 2249,
    "provider_count": 9,
    "top_providers": [
      {
        "provider": "Carrefour Banco",
        "clicks": 1593
      },
      {
        "provider": "Dub.link",
        "clicks": 248
      },
      {
        "provider": "Ualá",
        "clicks": 162
      },
      {
        "provider": "Fiwind",
        "clicks": 105
      },
      {
        "provider": "Naranja X",
        "clicks": 58
      }
    ]
  },
  {
    "category": "Criptomonedas",
    "total_clicks": 1921,
    "provider_count": 11,
    "top_providers": [
      {
        "provider": "Nexo",
        "clicks": 952
      },
      {
        "provider": "Dub.link",
        "clicks": 284
      },
      {
        "provider": "Lemon",
        "clicks": 243
      },
      {
        "provider": "Vesseo",
        "clicks": 221
      },
      {
        "provider": "Ripio",
        "clicks": 59
      }
    ]
  },
  {
    "category": "Billetera USD",
    "total_clicks": 1676,
    "provider_count": 3,
    "top_providers": [
      {
        "provider": "AstroPay",
        "clicks": 1139
      },
      {
        "provider": "Dub.link",
        "clicks": 377
      },
      {
        "provider": "LB",
        "clicks": 160
      }
    ]
  },
  {
    "category": "PF UVA pago periódico",
    "total_clicks": 662,
    "provider_count": 1,
    "top_providers": [
      {
        "provider": "Banco Nación",
        "clicks": 662
      }
    ]
  },
  {
    "category": "Renta Mixta",
    "total_clicks": 528,
    "provider_count": 2,
    "top_providers": [
      {
        "provider": "Cocos",
        "clicks": 360
      },
      {
        "provider": "Dub.link",
        "clicks": 168
      }
    ]
  },
  {
    "category": "Cuenta Remunerada USD",
    "total_clicks": 379,
    "provider_count": 4,
    "top_providers": [
      {
        "provider": "Banco Santander",
        "clicks": 144
      },
      {
        "provider": "Supervielle",
        "clicks": 94
      },
      {
        "provider": "Dub.link",
        "clicks": 76
      },
      {
        "provider": "Banco Nación",
        "clicks": 65
      }
    ]
  },
  {
    "category": "Retorno total",
    "total_clicks": 112,
    "provider_count": 1,
    "top_providers": [
      {
        "provider": "Cocos",
        "clicks": 112
      }
    ]
  },
  {
    "category": "ARGt",
    "total_clicks": 105,
    "provider_count": 2,
    "top_providers": [
      {
        "provider": "Belo",
        "clicks": 65
      },
      {
        "provider": "Dub.link",
        "clicks": 40
      }
    ]
  },
  {
    "category": "wARS",
    "total_clicks": 36,
    "provider_count": 2,
    "top_providers": [
      {
        "provider": "CapyFi",
        "clicks": 26
      },
      {
        "provider": "Ripio",
        "clicks": 10
      }
    ]
  },
  {
    "category": "PF UVA precancelable",
    "total_clicks": 11,
    "provider_count": 3,
    "top_providers": [
      {
        "provider": "Bna",
        "clicks": 7
      },
      {
        "provider": "Banco Provincia",
        "clicks": 2
      },
      {
        "provider": "BBVA",
        "clicks": 2
      }
    ]
  }
]