[
  {
    "date": "20260710",
    "categories": {
      "Página Amiga": 10,
      "Billetera": 10,
      "Cuenta Remunerada": 43,
      "Otro": 34,
      "Plazo Fijo": 16,
      "Money Market": 1,
      "Billetera USD": 5,
      "Cuenta Remunerada USD": 1,
      "Frascos": 17,
      "PF UVA pago periódico": 2,
      "General": 12,
      "Criptomonedas": 6,
      "plazo fijo tradicional": 14,
      "wARS": 2
    },
    "total": 173
  },
  {
    "date": "20260709",
    "categories": {
      "Página Amiga": 19,
      "Billetera": 50,
      "Cuenta Remunerada": 67,
      "Otro": 86,
      "Money Market": 7,
      "Criptomonedas": 25,
      "Plazo Fijo": 35,
      "ARGt": 1,
      "Billetera USD": 20,
      "Cuenta Remunerada USD": 1,
      "Frascos": 25,
      "PF UVA pago periódico": 3,
      "General": 17,
      "plazo fijo tradicional": 15,
      "wARS": 8
    },
    "total": 379
  },
  {
    "date": "20260708",
    "categories": {
      "Plazo Fijo": 118,
      "Cuenta Remunerada": 149,
      "Otro": 170,
      "Money Market": 5,
      "Página Amiga": 36,
      "Billetera": 37,
      "ARGt": 1,
      "Billetera USD": 5,
      "Cuenta Remunerada USD": 2,
      "Frascos": 33,
      "PF UVA pago periódico": 7,
      "PF UVA precancelable": 10,
      "General": 36,
      "Criptomonedas": 15,
      "plazo fijo tradicional": 43
    },
    "total": 667
  },
  {
    "date": "20260707",
    "categories": {
      "Página Amiga": 29,
      "Billetera": 76,
      "Cuenta Remunerada": 189,
      "Otro": 143,
      "Plazo Fijo": 84,
      "Money Market": 1,
      "Billetera USD": 11,
      "Cuenta Remunerada USD": 5,
      "Frascos": 24,
      "PF UVA pago periódico": 12,
      "PF UVA precancelable": 4,
      "General": 31,
      "Criptomonedas": 12,
      "plazo fijo tradicional": 22,
      "wARS": 7
    },
    "total": 650
  },
  {
    "date": "20260706",
    "categories": {
      "Money Market": 4,
      "Billetera": 42,
      "Página Amiga": 30,
      "Plazo Fijo": 45,
      "Cuenta Remunerada": 73,
      "Otro": 76
    },
    "total": 270
  }
]