[
  {
    "date": "20260721",
    "categories": {
      "Otro": 37,
      "Página Amiga": 15,
      "Billetera": 17,
      "Cuenta Remunerada": 32,
      "Money Market": 1,
      "Plazo Fijo": 18,
      "Billetera USD": 12,
      "Frascos": 15,
      "PF UVA pago periódico": 4,
      "PF UVA precancelable": 1,
      "General": 14,
      "Criptomonedas": 9,
      "plazo fijo tradicional": 18,
      "wARS": 3
    },
    "total": 196
  },
  {
    "date": "20260720",
    "categories": {
      "Otro": 95,
      "Página Amiga": 62,
      "Billetera": 47,
      "Cuenta Remunerada": 75,
      "Plazo Fijo": 50,
      "ARGt": 1,
      "Billetera USD": 16,
      "Frascos": 23,
      "PF UVA pago periódico": 2,
      "General": 7,
      "Criptomonedas": 21,
      "plazo fijo tradicional": 48,
      "wARS": 6
    },
    "total": 453
  },
  {
    "date": "20260719",
    "categories": {
      "Billetera": 19,
      "Cuenta Remunerada": 20,
      "Otro": 31,
      "Plazo Fijo": 15,
      "Billetera USD": 5,
      "Cuenta Remunerada USD": 1,
      "Frascos": 5,
      "PF UVA pago periódico": 1,
      "PF UVA precancelable": 1,
      "General": 4,
      "Criptomonedas": 8,
      "plazo fijo tradicional": 12,
      "wARS": 5
    },
    "total": 127
  },
  {
    "date": "20260718",
    "categories": {
      "Otro": 37,
      "Billetera": 32,
      "Plazo Fijo": 16,
      "Cuenta Remunerada": 23,
      "Money Market": 2,
      "Página Amiga": 2,
      "Criptomonedas": 12,
      "ARGt": 1,
      "Billetera USD": 8,
      "Frascos": 3,
      "PF UVA pago periódico": 7,
      "General": 10,
      "plazo fijo tradicional": 8,
      "wARS": 4
    },
    "total": 165
  },
  {
    "date": "20260717",
    "categories": {
      "Página Amiga": 27,
      "Cuenta Remunerada": 66,
      "Otro": 83,
      "Billetera": 43,
      "Plazo Fijo": 33,
      "Billetera USD": 15,
      "Cuenta Remunerada USD": 2,
      "Frascos": 18,
      "PF UVA pago periódico": 5,
      "PF UVA precancelable": 1,
      "General": 15,
      "Criptomonedas": 14,
      "plazo fijo tradicional": 35,
      "wARS": 2
    },
    "total": 359
  },
  {
    "date": "20260716",
    "categories": {
      "Página Amiga": 41,
      "Billetera": 28,
      "Cuenta Remunerada": 62,
      "Otro": 59,
      "Plazo Fijo": 17,
      "Criptomonedas": 1,
      "Billetera USD": 7,
      "Frascos": 18,
      "PF UVA pago periódico": 3
    },
    "total": 236
  }
]