{
  "legacy": [
    {
      "event_name": "click",
      "has_category": "sin_categoria",
      "total_clicks": 32011,
      "unique_providers": 136,
      "days_tracked": 71
    }
  ],
  "new_events": [
    {
      "event_name": "provider_click",
      "has_category": "con_categoria",
      "total_clicks": 17778,
      "unique_providers": 110,
      "days_tracked": 71
    },
    {
      "event_name": "sponsor_click",
      "has_category": "sin_categoria",
      "total_clicks": 1344,
      "unique_providers": 3,
      "days_tracked": 71
    }
  ],
  "summary": {
    "total_legacy": 32011,
    "total_new": 19122,
    "with_category": 17778,
    "without_category": 33355
  }
}