[
  {
    "provider": "Dub.link",
    "total_clicks": 10632,
    "days_active": 22
  },
  {
    "provider": "Carrefour Banco",
    "total_clicks": 1551,
    "days_active": 33
  },
  {
    "provider": "DolarApp",
    "total_clicks": 1257,
    "days_active": 22
  },
  {
    "provider": "IOL",
    "total_clicks": 981,
    "days_active": 13
  },
  {
    "provider": "Mercado Pago",
    "total_clicks": 925,
    "days_active": 13
  },
  {
    "provider": "Nexo",
    "total_clicks": 524,
    "days_active": 15
  },
  {
    "provider": "AstroPay",
    "total_clicks": 522,
    "days_active": 13
  },
  {
    "provider": "Reba",
    "total_clicks": 463,
    "days_active": 31
  },
  {
    "provider": "comparadolar.ar",
    "total_clicks": 424,
    "days_active": 33
  },
  {
    "provider": "Banco BICA",
    "total_clicks": 358,
    "days_active": 13
  }
]