[
  {
    "provider": "Dub.link",
    "total_clicks": 10639,
    "days_active": 22
  },
  {
    "provider": "IOL",
    "total_clicks": 4744,
    "days_active": 70
  },
  {
    "provider": "Carrefour Banco",
    "total_clicks": 4376,
    "days_active": 101
  },
  {
    "provider": "Banco Nación",
    "total_clicks": 4277,
    "days_active": 81
  },
  {
    "provider": "AstroPay",
    "total_clicks": 3753,
    "days_active": 81
  },
  {
    "provider": "Banco Voii",
    "total_clicks": 2984,
    "days_active": 65
  },
  {
    "provider": "Nexo",
    "total_clicks": 2876,
    "days_active": 67
  },
  {
    "provider": "Mercado Pago",
    "total_clicks": 2841,
    "days_active": 81
  },
  {
    "provider": "Cocos",
    "total_clicks": 2524,
    "days_active": 81
  },
  {
    "provider": "Ualá",
    "total_clicks": 2524,
    "days_active": 81
  }
]